eventstudy/__init__.py
eventstudy/eventStudy.py
eventstudy/eventStudyBatch.py
eventstudy/example_custom.py
eventstudy/excelExporter.py
eventstudy/exception.py
eventstudy/importer.py
eventstudy/models.py
eventstudy/multiple.py
eventstudy/single.py
eventstudy/test.py
eventstudy/utils.py
eventstudy-0.1a12.dist-info/LICENSE
eventstudy-0.1a12.dist-info/METADATA
eventstudy-0.1a12.dist-info/WHEEL
eventstudy-0.1a12.dist-info/top_level.txt
eventstudy-0.1a12.dist-info/RECORD
