Metadata-Version: 2.1
Name: eventstudy
Version: 0.1a12
Summary: Event Study package is an open-source python project created to facilitate the computation of financial event study analysis.
Home-page: https://github.com/LemaireJean-Baptiste/eventstudy
Author: Jean-Baptiste Lemaire
Author-email: lemaire.jeanbaptiste@gmail.com
License: UNKNOWN
Platform: UNKNOWN
Classifier: Programming Language :: Python :: 3
Classifier: License :: OSI Approved :: GNU General Public License v3 (GPLv3)
Classifier: Operating System :: OS Independent
Requires-Python: >=3.6
Requires-Dist: numpy
Requires-Dist: matplotlib
Requires-Dist: pandas
Requires-Dist: statsmodels
Requires-Dist: scipy
